pygeckocircuits2/__init__.py
pygeckocircuits2/geckoCircuitsRemote.py
pygeckocircuits2-0.0.4.dist-info/METADATA
pygeckocircuits2-0.0.4.dist-info/WHEEL
pygeckocircuits2-0.0.4.dist-info/RECORD
