Metadata-Version: 2.3
Name: pygeckocircuits2
Version: 0.0.4
Summary: Control GeckoCircuits by using python.
Project-URL: Homepage, https://github.com/upb-lea/pygeckocircuits2
Project-URL: Issues, https://github.com/upb-lea/pygeckocircuits2/issues
Author: UPB-LEA
Classifier: License :: OSI Approved :: MIT License
Classifier: Operating System :: OS Independent
Classifier: Programming Language :: Python :: 3
Requires-Python: ~=3.8
Requires-Dist: pandas
Requires-Dist: pyjnius
